fortisx/__init__.py
fortisx/client.py
fortisx/py.typed
fortisx-0.1.0.dist-info/LICENSE
fortisx-0.1.0.dist-info/METADATA
fortisx-0.1.0.dist-info/WHEEL
fortisx-0.1.0.dist-info/top_level.txt
fortisx-0.1.0.dist-info/RECORD
