Metadata-Version: 2.1
Name: fortisx
Version: 0.1.0
Summary: FortisX Python SDK
Author-email: Fortisx Developers <dev@fortisx.fi>
License: MIT
Project-URL: Homepage, https://github.com/fortisx/python-sdk
Project-URL: Documentation, https://fortisx.gitbook.io/docs/introduction/python-sdk
Project-URL: Issues, https://github.com/fortisx/python-sdk/issues
Classifier: Programming Language :: Python :: 3
Classifier: Programming Language :: Python :: 3 :: Only
Classifier: License :: OSI Approved :: MIT License
Classifier: Operating System :: OS Independent
Classifier: Typing :: Typed
Classifier: Development Status :: 4 - Beta
Classifier: Intended Audience :: Developers
Classifier: Topic :: Software Development :: Libraries :: Python Modules
Requires-Python: >=3.8
License-File: LICENSE
